fairpyx/README.md
fairpyx/VERSION
fairpyx/__init__.py
fairpyx/adaptors.py
fairpyx/allocations.py
fairpyx/explanations.py
fairpyx/instances.py
fairpyx/satisfaction.py
fairpyx/algorithms/__init__.py
fairpyx/algorithms/almost_egalitarian.py
fairpyx/algorithms/fractional_egalitarian.py
fairpyx/algorithms/iterated_maximum_matching.py
fairpyx/algorithms/picking_sequence.py
fairpyx/algorithms/picking_sequence_demo.py
fairpyx/algorithms/utilitarian_matching.py
fairpyx/utils/__init__.py
fairpyx/utils/graph_utils.py
fairpyx/utils/linear_programming_utils.py
fairpyx/utils/solve.py
fairpyx/utils/test_utils.py
fairpyx/zalternatives/yekta_day_impl/README.md
fairpyx-0.0.4.dist-info/LICENSE
fairpyx-0.0.4.dist-info/METADATA
fairpyx-0.0.4.dist-info/WHEEL
fairpyx-0.0.4.dist-info/top_level.txt
fairpyx-0.0.4.dist-info/RECORD
